qiskit_qutrit_calibration/VERSION.txt
qiskit_qutrit_calibration/__init__.py
qiskit_qutrit_calibration/framework/__init__.py
qiskit_qutrit_calibration/framework/calibrations.py
qiskit_qutrit_calibration/framework/gate_library.py
qiskit_qutrit_calibration/framework/multi_analyses.py
qiskit_qutrit_calibration/framework/utils.py
qiskit_qutrit_calibration/library/__init__.py
qiskit_qutrit_calibration/library/ef_fine_amp.py
qiskit_qutrit_calibration/library/ef_rough_amp.py
qiskit_qutrit_calibration/library/ef_roughdrag.py
qiskit_qutrit_calibration/library/ef_spectroscopy.py
qiskit_qutrit_calibration/library/ef_standard_rb.py
qiskit_qutrit_calibration/library/qutrit_gates.py
qiskit_qutrit_calibration/version.py
qiskit_qutrit_calibration-0.1.4.dist-info/LICENSE.txt
qiskit_qutrit_calibration-0.1.4.dist-info/METADATA
qiskit_qutrit_calibration-0.1.4.dist-info/WHEEL
qiskit_qutrit_calibration-0.1.4.dist-info/RECORD
