Metadata-Version: 2.1
Name: qiskit-qutrit-calibration
Version: 0.1.4
Summary: A qiskit experiments extension to calibrate single qutrit gates.
Author: Naoki Kanazawa
Maintainer: Kaelyn Ferris
Requires-Python: >=3.8,<4.0
Classifier: Programming Language :: Python :: 3
Classifier: Programming Language :: Python :: 3.8
Classifier: Programming Language :: Python :: 3.9
Classifier: Programming Language :: Python :: 3.10
Classifier: Programming Language :: Python :: 3.11
Classifier: Programming Language :: Python :: 3.12
Requires-Dist: qiskit-experiments (>=0.5.4,<0.6.0)
Requires-Dist: qiskit-ibm-provider (>=0.8.0,<0.9.0)
Requires-Dist: setuptools (>=69.0.3,<70.0.0)
